jupyterlab/__init__.py
jupyterlab/lab.html
jupyterlab/labapp.py
jupyterlab/build/012cf6a10129e2275d79d6adac7f3b02.woff
jupyterlab/build/04a5ee7f2a6c642f5705f7df873a1f24.png
jupyterlab/build/04df298d4d61db8edc888752745188ae.png
jupyterlab/build/0662c22d4e544cecf2bc66ee4c761ed6.svg
jupyterlab/build/1.bundle.js
jupyterlab/build/1dc35d25e61d819a9c357074014867ab.ttf
jupyterlab/build/25a32416abee198dd821b0b17a198a8f.eot
jupyterlab/build/28f2f5e6ac027acb7fbd41f7e02ebf90.gif
jupyterlab/build/2b609d364e2e1d67ba33a81c58d9eb8a.svg
jupyterlab/build/2b912f7c0653008ca28ebacda49025e7.gif
jupyterlab/build/324b4fcaf164735c627269504b7bc28e.png
jupyterlab/build/526043fecdd7256ac10bad4f823106c2.png
jupyterlab/build/570eb83859dc23dd0eec423a49e147fe.woff2
jupyterlab/build/585392137cf5132c9aeb8de9cf729be6.png
jupyterlab/build/5db425e1bb5ba30e906a9e729d519e28.png
jupyterlab/build/5e9fca8da62c2b939b204d8883012664.gif
jupyterlab/build/67210cba51efc06308353fa274b6d389.svg
jupyterlab/build/6a373d461dc6968f4731c7fb1290eb3f.png
jupyterlab/build/7cb0d2482ecadc1b80eb0abe457371b6.png
jupyterlab/build/88bce39a36f4e4c6186745b8df0bc60e.png
jupyterlab/build/899a0c289a928e6bc3bb14ab1f551df0.svg
jupyterlab/build/9079851651d427c3c2241567b2b49edc.html
jupyterlab/build/90c599d828988b99f5f683dbcb7454fe.png
jupyterlab/build/9101d59cbaae907090ec73466b2ae2af.png
jupyterlab/build/930dde33391603fade73980cf67feb4e.svg
jupyterlab/build/a37b0c01c0baf1888ca812cc0508f6e2.ttf
jupyterlab/build/a5f896d73c05dd2cec16fd54f7b6d38b.svg
jupyterlab/build/afa9fddb92eb250e309d9148bb62f43f.png
jupyterlab/build/b80c321cdb09746d881e6b9227fa4491.png
jupyterlab/build/bundle.js
jupyterlab/build/c21ec2fd0054b39327298bf6cb158de4.png
jupyterlab/build/c8ddf1e5e5bf3682bc7bebf30f394148.woff
jupyterlab/build/cdbbf3faea3d6d5b7c7c8a27736254df.gif
jupyterlab/build/d7c639084f684d66a1bc66855d193ed8.svg
jupyterlab/build/e6120fce13c9ba723d6565925abe780e.html
jupyterlab_emrys-0.1.4.dist-info/DESCRIPTION.rst
jupyterlab_emrys-0.1.4.dist-info/METADATA
jupyterlab_emrys-0.1.4.dist-info/RECORD
jupyterlab_emrys-0.1.4.dist-info/WHEEL
jupyterlab_emrys-0.1.4.dist-info/entry_points.txt
jupyterlab_emrys-0.1.4.dist-info/metadata.json
jupyterlab_emrys-0.1.4.dist-info/top_level.txt
