Metadata-Version: 2.0
Name: jupyterlab-emrys
Version: 0.1.4
Summary: An Emrys flavored Jupyter lab environment notebook server extension.
Home-page: http://projectemrys.com
Author: Emrys Dev Team
Author-email: peter@projectemrys.com
License: UNKNOWN
Keywords: ipython,jupyter,Web,emrys
Platform: UNKNOWN
Classifier: Development Status :: 3 - Alpha
Classifier: Intended Audience :: Developers
Classifier: Intended Audience :: Science/Research
Classifier: License :: OSI Approved :: BSD License
Classifier: Programming Language :: Python :: 2
Classifier: Programming Language :: Python :: 2.7
Classifier: Programming Language :: Python :: 3
Requires-Dist: notebook (>=4.2.0)
